{
  "base": "USD",
  "disclaimer": "Exchange rates are provided for informational purposes only, and do not constitute financial advice of any kind. Although every attempt is made to ensure quality, NO guarantees are given whatsoever of accuracy, validity, availability, or fitness for any purpose - please use at your own risk. All usage is subject to your acceptance of the Terms and Conditions of Service, available at: http://openexchangerates.org/terms/",
  "license": "Data sourced from various providers with public-facing APIs; copyright may apply; resale is prohibited; no warranties given of any kind. All usage is subject to your acceptance of the License Agreement available at: http://openexchangerates.org/license/",
  "rates": [
    {
      "code": "AED",
      "value": 3.673123
    },
    {
      "code": "AFN",
      "value": 52.97
    },
    {
      "code": "ALL",
      "value": 107.257376
    },
    {
      "code": "AMD",
      "value": 417.719998
    },
    {
      "code": "ANG",
      "value": 1.788875
    },
    {
      "code": "AOA",
      "value": 95.980099
    },
    {
      "code": "ARS",
      "value": 5.086931
    },
    {
      "code": "AUD",
      "value": 0.961588
    },
    {
      "code": "AWG",
      "value": 1.790133
    },
    {
      "code": "AZN",
      "value": 0.7848
    },
    {
      "code": "BAM",
      "value": 1.500927
    },
    {
      "code": "BBD",
      "value": 2
    },
    {
      "code": "BDT",
      "value": 78.701388
    },
    {
      "code": "BGN",
      "value": 1.501035
    },
    {
      "code": "BHD",
      "value": 0.377017
    },
    {
      "code": "BIF",
      "value": 1558.55875
    },
    {
      "code": "BMD",
      "value": 1
    },
    {
      "code": "BND",
      "value": 1.249021
    },
    {
      "code": "BOB",
      "value": 6.992528
    },
    {
      "code": "BRL",
      "value": 1.975818
    },
    {
      "code": "BSD",
      "value": 1
    },
    {
      "code": "BTC",
      "value": 0.021322
    },
    {
      "code": "BTN",
      "value": 54.137549
    },
    {
      "code": "BWP",
      "value": 8.20552
    },
    {
      "code": "BYR",
      "value": 8650.791667
    },
    {
      "code": "BZD",
      "value": 1.975893
    },
    {
      "code": "CAD",
      "value": 1.021148
    },
    {
      "code": "CDF",
      "value": 929.204842
    },
    {
      "code": "CHF",
      "value": 0.942143
    },
    {
      "code": "CLF",
      "value": 0.02063
    },
    {
      "code": "CLP",
      "value": 471.286047
    },
    {
      "code": "CNY",
      "value": 6.227364
    },
    {
      "code": "COP",
      "value": 1798.52223
    },
    {
      "code": "CRC",
      "value": 500.241202
    },
    {
      "code": "CUP",
      "value": 22.687419
    },
    {
      "code": "CVE",
      "value": 84.680162
    },
    {
      "code": "CZK",
      "value": 19.604769
    },
    {
      "code": "DJF",
      "value": 177.42425
    },
    {
      "code": "DKK",
      "value": 5.718432
    },
    {
      "code": "DOP",
      "value": 41.138854
    },
    {
      "code": "DZD",
      "value": 79.044477
    },
    {
      "code": "EEK",
      "value": 11.7331
    },
    {
      "code": "EGP",
      "value": 6.781366
    },
    {
      "code": "ETB",
      "value": 18.467937
    },
    {
      "code": "EUR",
      "value": 0.765576
    },
    {
      "code": "FJD",
      "value": 1.786058
    },
    {
      "code": "FKP",
      "value": 0.66151
    },
    {
      "code": "GBP",
      "value": 0.66151
    },
    {
      "code": "GEL",
      "value": 1.6595
    },
    {
      "code": "GHS",
      "value": 1.934486
    },
    {
      "code": "GIP",
      "value": 0.625803
    },
    {
      "code": "GMD",
      "value": 33.278563
    },
    {
      "code": "GNF",
      "value": 7103.41625
    },
    {
      "code": "GTQ",
      "value": 7.808081
    },
    {
      "code": "GYD",
      "value": 202.634999
    },
    {
      "code": "HKD",
      "value": 7.75956
    },
    {
      "code": "HNL",
      "value": 19.788746
    },
    {
      "code": "HRK",
      "value": 5.817952
    },
    {
      "code": "HTG",
      "value": 42.5301
    },
    {
      "code": "HUF",
      "value": 233.76234
    },
    {
      "code": "IDR",
      "value": 9704.938572
    },
    {
      "code": "ILS",
      "value": 3.685638
    },
    {
      "code": "INR",
      "value": 54.076979
    },
    {
      "code": "IQD",
      "value": 1157.92875
    },
    {
      "code": "IRR",
      "value": 12285.345
    },
    {
      "code": "ISK",
      "value": 125.302501
    },
    {
      "code": "JEP",
      "value": 0.66151
    },
    {
      "code": "JMD",
      "value": 96.827113
    },
    {
      "code": "JOD",
      "value": 0.707982
    },
    {
      "code": "JPY",
      "value": 95.609886
    },
    {
      "code": "KES",
      "value": 85.608457
    },
    {
      "code": "KGS",
      "value": 47.858266
    },
    {
      "code": "KHR",
      "value": 3987.8775
    },
    {
      "code": "KMF",
      "value": 377.220615
    },
    {
      "code": "KPW",
      "value": 900
    },
    {
      "code": "KRW",
      "value": 1109.796232
    },
    {
      "code": "KWD",
      "value": 0.284278
    },
    {
      "code": "KYD",
      "value": 0.820555
    },
    {
      "code": "KZT",
      "value": 150.780781
    },
    {
      "code": "LAK",
      "value": 7851.63625
    },
    {
      "code": "LBP",
      "value": 1505.06188
    },
    {
      "code": "LKR",
      "value": 126.187526
    },
    {
      "code": "LRD",
      "value": 74.383333
    },
    {
      "code": "LSL",
      "value": 9.199316
    },
    {
      "code": "LTL",
      "value": 2.648481
    },
    {
      "code": "LVL",
      "value": 0.53793
    },
    {
      "code": "LYD",
      "value": 1.279685
    },
    {
      "code": "MAD",
      "value": 8.527946
    },
    {
      "code": "MDL",
      "value": 12.323814
    },
    {
      "code": "MGA",
      "value": 2216.985
    },
    {
      "code": "MKD",
      "value": 47.19144
    },
    {
      "code": "MMK",
      "value": 874.256625
    },
    {
      "code": "MNT",
      "value": 1388.166667
    },
    {
      "code": "MOP",
      "value": 7.994958
    },
    {
      "code": "MRO",
      "value": 292.606375
    },
    {
      "code": "MUR",
      "value": 31.109088
    },
    {
      "code": "MVR",
      "value": 15.396925
    },
    {
      "code": "MWK",
      "value": 380.682185
    },
    {
      "code": "MXN",
      "value": 12.434061
    },
    {
      "code": "MYR",
      "value": 3.119679
    },
    {
      "code": "MZN",
      "value": 30.133334
    },
    {
      "code": "NAD",
      "value": 9.193346
    },
    {
      "code": "NGN",
      "value": 158.91088
    },
    {
      "code": "NIO",
      "value": 24.670912
    },
    {
      "code": "NOK",
      "value": 5.762094
    },
    {
      "code": "NPR",
      "value": 86.636943
    },
    {
      "code": "NZD",
      "value": 1.208617
    },
    {
      "code": "OMR",
      "value": 0.385022
    },
    {
      "code": "PAB",
      "value": 1
    },
    {
      "code": "PEN",
      "value": 2.594957
    },
    {
      "code": "PGK",
      "value": 2.075817
    },
    {
      "code": "PHP",
      "value": 40.585481
    },
    {
      "code": "PKR",
      "value": 98.024625
    },
    {
      "code": "PLN",
      "value": 3.182794
    },
    {
      "code": "PYG",
      "value": 4016.658852
    },
    {
      "code": "QAR",
      "value": 3.640586
    },
    {
      "code": "RON",
      "value": 3.365827
    },
    {
      "code": "RSD",
      "value": 85.654865
    },
    {
      "code": "RUB",
      "value": 30.68165
    },
    {
      "code": "RWF",
      "value": 641.183316
    },
    {
      "code": "SAR",
      "value": 3.750229
    },
    {
      "code": "SBD",
      "value": 7.096078
    },
    {
      "code": "SCR",
      "value": 11.669763
    },
    {
      "code": "SDG",
      "value": 4.414932
    },
    {
      "code": "SEK",
      "value": 6.408834
    },
    {
      "code": "SGD",
      "value": 1.248329
    },
    {
      "code": "SHP",
      "value": 0.66151
    },
    {
      "code": "SLL",
      "value": 4320.336208
    },
    {
      "code": "SOS",
      "value": 1605.20625
    },
    {
      "code": "SRD",
      "value": 3.275
    },
    {
      "code": "STD",
      "value": 18905.4025
    },
    {
      "code": "SVC",
      "value": 8.751136
    },
    {
      "code": "SYP",
      "value": 70.817113
    },
    {
      "code": "SZL",
      "value": 9.195876
    },
    {
      "code": "THB",
      "value": 29.560261
    },
    {
      "code": "TJS",
      "value": 4.754533
    },
    {
      "code": "TMT",
      "value": 2.85275
    },
    {
      "code": "TND",
      "value": 1.571364
    },
    {
      "code": "TOP",
      "value": 1.751752
    },
    {
      "code": "TRY",
      "value": 1.809044
    },
    {
      "code": "TTD",
      "value": 6.421454
    },
    {
      "code": "TWD",
      "value": 29.73623
    },
    {
      "code": "TZS",
      "value": 1624.343252
    },
    {
      "code": "UAH",
      "value": 8.1307
    },
    {
      "code": "UGX",
      "value": 2641.25353
    },
    {
      "code": "USD",
      "value": 1
    },
    {
      "code": "UYU",
      "value": 18.972299
    },
    {
      "code": "UZS",
      "value": 2037.52351
    },
    {
      "code": "VEF",
      "value": 4.295129
    },
    {
      "code": "VND",
      "value": 20920.12866
    },
    {
      "code": "VUV",
      "value": 91.213333
    },
    {
      "code": "WST",
      "value": 2.300326
    },
    {
      "code": "XAF",
      "value": 502.93199
    },
    {
      "code": "XCD",
      "value": 2.701275
    },
    {
      "code": "XDR",
      "value": 0.6632
    },
    {
      "code": "XOF",
      "value": 503.13575
    },
    {
      "code": "XPF",
      "value": 91.530038
    },
    {
      "code": "YER",
      "value": 214.877361
    },
    {
      "code": "ZAR",
      "value": 9.193608
    },
    {
      "code": "ZMK",
      "value": 5232.196666
    },
    {
      "code": "ZMW",
      "value": 5.398728
    },
    {
      "code": "ZWL",
      "value": 322.322775
    }
  ],
  "timestamp": 1363388400
}