{
  "base": "USD",
  "disclaimer": "Exchange rates are provided for informational purposes only, and do not constitute financial advice of any kind. Although every attempt is made to ensure quality, NO guarantees are given whatsoever of accuracy, validity, availability, or fitness for any purpose - please use at your own risk. All usage is subject to your acceptance of the Terms and Conditions of Service, available at: https://openexchangerates.org/terms/",
  "license": "Data sourced from various providers with public-facing APIs; copyright may apply; resale is prohibited; no warranties given of any kind. All usage is subject to your acceptance of the License Agreement available at: https://openexchangerates.org/license/",
  "rates": [
    {
      "code": "AED",
      "value": 3.672783
    },
    {
      "code": "AFN",
      "value": 57.14485
    },
    {
      "code": "ALL",
      "value": 103.9951
    },
    {
      "code": "AMD",
      "value": 408.939003
    },
    {
      "code": "ANG",
      "value": 1.78902
    },
    {
      "code": "AOA",
      "value": 97.297951
    },
    {
      "code": "ARS",
      "value": 5.975501
    },
    {
      "code": "AUD",
      "value": 1.06821
    },
    {
      "code": "AWG",
      "value": 1.78985
    },
    {
      "code": "AZN",
      "value": 0.784167
    },
    {
      "code": "BAM",
      "value": 1.452913
    },
    {
      "code": "BBD",
      "value": 2
    },
    {
      "code": "BDT",
      "value": 77.528659
    },
    {
      "code": "BGN",
      "value": 1.455655
    },
    {
      "code": "BHD",
      "value": 0.37698
    },
    {
      "code": "BIF",
      "value": 1547.7851
    },
    {
      "code": "BMD",
      "value": 1
    },
    {
      "code": "BND",
      "value": 1.245415
    },
    {
      "code": "BOB",
      "value": 6.894613
    },
    {
      "code": "BRL",
      "value": 2.33373
    },
    {
      "code": "BSD",
      "value": 1
    },
    {
      "code": "BTC",
      "value": 0.00251665
    },
    {
      "code": "BTN",
      "value": 63.500213
    },
    {
      "code": "BWP",
      "value": 8.6925
    },
    {
      "code": "BYR",
      "value": 9307.88
    },
    {
      "code": "BZD",
      "value": 1.990737
    },
    {
      "code": "CAD",
      "value": 1.04576
    },
    {
      "code": "CDF",
      "value": 920.316667
    },
    {
      "code": "CHF",
      "value": 0.914739
    },
    {
      "code": "CLF",
      "value": 0.022395
    },
    {
      "code": "CLP",
      "value": 520.752204
    },
    {
      "code": "CNY",
      "value": 6.109028
    },
    {
      "code": "COP",
      "value": 1932.59
    },
    {
      "code": "CRC",
      "value": 500.9802
    },
    {
      "code": "CUP",
      "value": 22.682881
    },
    {
      "code": "CVE",
      "value": 81.96244
    },
    {
      "code": "CZK",
      "value": 20.09366
    },
    {
      "code": "DJF",
      "value": 177.466999
    },
    {
      "code": "DKK",
      "value": 5.536391
    },
    {
      "code": "DOP",
      "value": 42.44077
    },
    {
      "code": "DZD",
      "value": 80.45113
    },
    {
      "code": "EEK",
      "value": 11.699125
    },
    {
      "code": "EGP",
      "value": 6.889396
    },
    {
      "code": "ERN",
      "value": 15.002825
    },
    {
      "code": "ETB",
      "value": 18.97952
    },
    {
      "code": "EUR",
      "value": 0.741361
    },
    {
      "code": "FJD",
      "value": 1.847901
    },
    {
      "code": "FKP",
      "value": 0.623142
    },
    {
      "code": "GBP",
      "value": 0.623142
    },
    {
      "code": "GEL",
      "value": 1.677
    },
    {
      "code": "GHS",
      "value": 2.227704
    },
    {
      "code": "GIP",
      "value": 0.623142
    },
    {
      "code": "GMD",
      "value": 32.607739
    },
    {
      "code": "GNF",
      "value": 7011.428667
    },
    {
      "code": "GTQ",
      "value": 7.864789
    },
    {
      "code": "GYD",
      "value": 201.761666
    },
    {
      "code": "HKD",
      "value": 7.75323
    },
    {
      "code": "HNL",
      "value": 20.33766
    },
    {
      "code": "HRK",
      "value": 5.657458
    },
    {
      "code": "HTG",
      "value": 42.39047
    },
    {
      "code": "HUF",
      "value": 221.681199
    },
    {
      "code": "IDR",
      "value": 11602
    },
    {
      "code": "ILS",
      "value": 3.52609
    },
    {
      "code": "INR",
      "value": 63.4059
    },
    {
      "code": "IQD",
      "value": 1163.73
    },
    {
      "code": "IRR",
      "value": 24903.25
    },
    {
      "code": "ISK",
      "value": 122.622001
    },
    {
      "code": "JEP",
      "value": 0.623142
    },
    {
      "code": "JMD",
      "value": 103.78975
    },
    {
      "code": "JOD",
      "value": 0.706549
    },
    {
      "code": "JPY",
      "value": 99.28494
    },
    {
      "code": "KES",
      "value": 86.289831
    },
    {
      "code": "KGS",
      "value": 48.637275
    },
    {
      "code": "KHR",
      "value": 4003.809667
    },
    {
      "code": "KMF",
      "value": 365.372148
    },
    {
      "code": "KPW",
      "value": 900
    },
    {
      "code": "KRW",
      "value": 1071.82335
    },
    {
      "code": "KWD",
      "value": 0.283511
    },
    {
      "code": "KYD",
      "value": 0.82136
    },
    {
      "code": "KZT",
      "value": 152.765
    },
    {
      "code": "LAK",
      "value": 7943.166667
    },
    {
      "code": "LBP",
      "value": 1506.668333
    },
    {
      "code": "LKR",
      "value": 131.095101
    },
    {
      "code": "LRD",
      "value": 80.511633
    },
    {
      "code": "LSL",
      "value": 10.3106
    },
    {
      "code": "LTL",
      "value": 2.563866
    },
    {
      "code": "LVL",
      "value": 0.521862
    },
    {
      "code": "LYD",
      "value": 1.253819
    },
    {
      "code": "MAD",
      "value": 8.30996
    },
    {
      "code": "MDL",
      "value": 12.89674
    },
    {
      "code": "MGA",
      "value": 2238.343333
    },
    {
      "code": "MKD",
      "value": 45.73094
    },
    {
      "code": "MMK",
      "value": 969.69412
    },
    {
      "code": "MNT",
      "value": 1700
    },
    {
      "code": "MOP",
      "value": 7.967951
    },
    {
      "code": "MRO",
      "value": 299.4885
    },
    {
      "code": "MTL",
      "value": 0.683602
    },
    {
      "code": "MUR",
      "value": 30.63758
    },
    {
      "code": "MVR",
      "value": 15.34068
    },
    {
      "code": "MWK",
      "value": 394.93475
    },
    {
      "code": "MXN",
      "value": 13.05431
    },
    {
      "code": "MYR",
      "value": 3.210835
    },
    {
      "code": "MZN",
      "value": 29.99585
    },
    {
      "code": "NAD",
      "value": 10.32378
    },
    {
      "code": "NGN",
      "value": 159.186401
    },
    {
      "code": "NIO",
      "value": 24.94229
    },
    {
      "code": "NOK",
      "value": 6.16899
    },
    {
      "code": "NPR",
      "value": 100.658401
    },
    {
      "code": "NZD",
      "value": 1.206572
    },
    {
      "code": "OMR",
      "value": 0.385004
    },
    {
      "code": "PAB",
      "value": 1
    },
    {
      "code": "PEN",
      "value": 2.797277
    },
    {
      "code": "PGK",
      "value": 2.5807
    },
    {
      "code": "PHP",
      "value": 43.72312
    },
    {
      "code": "PKR",
      "value": 107.387
    },
    {
      "code": "PLN",
      "value": 3.116139
    },
    {
      "code": "PYG",
      "value": 4429.280052
    },
    {
      "code": "QAR",
      "value": 3.640899
    },
    {
      "code": "RON",
      "value": 3.311348
    },
    {
      "code": "RSD",
      "value": 84.61456
    },
    {
      "code": "RUB",
      "value": 32.77884
    },
    {
      "code": "RWF",
      "value": 671.18824
    },
    {
      "code": "SAR",
      "value": 3.750381
    },
    {
      "code": "SBD",
      "value": 7.199552
    },
    {
      "code": "SCR",
      "value": 12.01225
    },
    {
      "code": "SDG",
      "value": 4.4291
    },
    {
      "code": "SEK",
      "value": 6.635965
    },
    {
      "code": "SGD",
      "value": 1.246846
    },
    {
      "code": "SHP",
      "value": 0.623142
    },
    {
      "code": "SLL",
      "value": 4316.666833
    },
    {
      "code": "SOS",
      "value": 1221.560367
    },
    {
      "code": "SRD",
      "value": 3.283333
    },
    {
      "code": "STD",
      "value": 18152.488267
    },
    {
      "code": "SVC",
      "value": 8.728404
    },
    {
      "code": "SYP",
      "value": 139.896749
    },
    {
      "code": "SZL",
      "value": 10.30884
    },
    {
      "code": "THB",
      "value": 31.53227
    },
    {
      "code": "TJS",
      "value": 4.77175
    },
    {
      "code": "TMT",
      "value": 2.853333
    },
    {
      "code": "TND",
      "value": 1.660731
    },
    {
      "code": "TOP",
      "value": 1.818435
    },
    {
      "code": "TRY",
      "value": 2.044764
    },
    {
      "code": "TTD",
      "value": 6.384655
    },
    {
      "code": "TWD",
      "value": 29.58399
    },
    {
      "code": "TZS",
      "value": 1608.583333
    },
    {
      "code": "UAH",
      "value": 8.177116
    },
    {
      "code": "UGX",
      "value": 2520.873333
    },
    {
      "code": "USD",
      "value": 1
    },
    {
      "code": "UYU",
      "value": 21.46358
    },
    {
      "code": "UZS",
      "value": 2177.096686
    },
    {
      "code": "VEF",
      "value": 6.291669
    },
    {
      "code": "VND",
      "value": 21097.533333
    },
    {
      "code": "VUV",
      "value": 94.705
    },
    {
      "code": "WST",
      "value": 2.314917
    },
    {
      "code": "XAF",
      "value": 487.336419
    },
    {
      "code": "XAG",
      "value": 0.04869631
    },
    {
      "code": "XAU",
      "value": 0.00077997
    },
    {
      "code": "XCD",
      "value": 2.70136
    },
    {
      "code": "XDR",
      "value": 0.65425
    },
    {
      "code": "XOF",
      "value": 487.3601
    },
    {
      "code": "XPF",
      "value": 88.699491
    },
    {
      "code": "YER",
      "value": 215.0382
    },
    {
      "code": "ZAR",
      "value": 10.30023
    },
    {
      "code": "ZMK",
      "value": 5221.025
    },
    {
      "code": "ZMW",
      "value": 5.523582
    },
    {
      "code": "ZWL",
      "value": 322.355006
    }
  ],
  "timestamp": 1384383600
}